pmusic/__init__.py
pmusic/pmusicFetch.py
pmusic/pmusicGenerate.py
pmusic-1.0.0rc1.dist-info/DESCRIPTION.rst
pmusic-1.0.0rc1.dist-info/METADATA
pmusic-1.0.0rc1.dist-info/RECORD
pmusic-1.0.0rc1.dist-info/WHEEL
pmusic-1.0.0rc1.dist-info/metadata.json
pmusic-1.0.0rc1.dist-info/top_level.txt
