Metadata-Version: 2.0
Name: pmusic
Version: 1.0.0rc1
Summary: Generate music in python
Home-page: https://github.com/The-SecondComing/pmusic
Author: the-second-coming
Author-email: alex.pmcoombes@gmail.com
License: None
Keywords: procedural music python
Platform: UNKNOWN
Classifier: Development Status :: 3 - Alpha
Classifier: Intended Audience :: Developers
Classifier: Topic :: Software Development :: Build Tools
Classifier: Programming Language :: Python :: 3.6
